pypsa2smspp/__init__.py
pypsa2smspp/constants.py
pypsa2smspp/inverse.py
pypsa2smspp/io_parser.py
pypsa2smspp/network_correction.py
pypsa2smspp/pip_utils.py
pypsa2smspp/transformation.py
pypsa2smspp/transformation_config.py
pypsa2smspp/utils.py
pypsa2smspp/data/config_default.yaml
pypsa2smspp/data/smspp_parameters.xlsx
pypsa2smspp-0.0.2.dist-info/licenses/LICENSE
pypsa2smspp-0.0.2.dist-info/METADATA
pypsa2smspp-0.0.2.dist-info/WHEEL
pypsa2smspp-0.0.2.dist-info/top_level.txt
pypsa2smspp-0.0.2.dist-info/RECORD
