Metadata-Version: 2.4
Name: pypsa2smspp
Version: 0.0.2
Summary: Bi-directional interface between PyPSA and SMS++
Author-email: Alessandro Pampado <alessandro.pampado@ing.unipi.it>, Davide Fioriti <davide.fioriti@unipi.it>, Unipi developers <davide.fioriti@unipi.it>
Project-URL: Homepage, https://github.com/SPSUnipi/pypsa2smspp
Project-URL: Issues, https://github.com/SPSUnipi/pypsa2smspp/issues
Classifier: Programming Language :: Python :: 3.12
Classifier: Programming Language :: Python :: 3.13
Classifier: License :: OSI Approved :: GNU General Public License v3 or later (GPLv3+)
Classifier: Operating System :: OS Independent
Requires-Python: >=3.12
License-File: LICENSE
Requires-Dist: numpy
Requires-Dist: pandas<3,>=0.24
Requires-Dist: pypsa>=1
Requires-Dist: xarray
Requires-Dist: openpyxl
Requires-Dist: pysmspp>=0.0.2
Provides-Extra: dev
Requires-Dist: pytest; extra == "dev"
Requires-Dist: highspy; extra == "dev"
Requires-Dist: gurobipy; extra == "dev"
Requires-Dist: coverage; extra == "dev"
Requires-Dist: pre-commit; extra == "dev"
Requires-Dist: ncompare; extra == "dev"
Requires-Dist: mypy; extra == "dev"
Provides-Extra: docs
Requires-Dist: numpydoc; extra == "docs"
Requires-Dist: sphinx; extra == "docs"
Requires-Dist: sphinx-book-theme; extra == "docs"
Requires-Dist: sphinx-rtd-theme; extra == "docs"
Requires-Dist: pydata-sphinx-theme; extra == "docs"
Requires-Dist: sphinx-reredirects; extra == "docs"
Requires-Dist: nbsphinx; extra == "docs"
Requires-Dist: nbsphinx-link; extra == "docs"
Requires-Dist: scikit-learn; extra == "docs"
Requires-Dist: ipython; extra == "docs"
Requires-Dist: ipykernel; extra == "docs"
Dynamic: license-file
